setup.py
cameo_panda/__init__.py
cameo_panda/__main__.py
cameo_panda.egg-info/PKG-INFO
cameo_panda.egg-info/SOURCES.txt
cameo_panda.egg-info/dependency_links.txt
cameo_panda.egg-info/requires.txt
cameo_panda.egg-info/top_level.txt