Metadata-Version: 1.1
Name: cameo-panda
Version: 0.5.5
Summary: This is a cameo_panda note️
Home-page: https://github.com/panda19931217/cameo_panda
Author: Bowen Chiu
Author-email: panda19931217@gmail.com
License: BSD 2-clause
Platform: UNKNOWN
Classifier: Programming Language :: Python :: 3
